Workbook

Sheet Instructions
B2: OHIO CORPORATION - STUDENT PROJECT
B3: Excel INDEX, MATCH & SUMIF Analysis Project
C4: © 2026 Mohim By Momina. All rights reserved
B6: Student Information
B8: Name: | C8: [Enter your name here]
B9: Student ID: | C9: [Enter your ID here]
B10: Date: | C10: [Enter date here]
B13: Project Overview
B15: This project will test your ability to use advanced Excel functions to analyze financial data from the Ohio Corporation. You will work with data from 7 retail stores and create formulas to extract insights and build a dashboard. Complete all three exercises and submit this file. unhide the sheets to get started
B20: Exercise List
B22: Exercise | C22: Topic | D22: Description | E22: Points
B23: Exercise 1 | C23: INDEX & MATCH | D23: Retrieve financial data using lookup functions | E23: 30 points
B24: Exercise 2 | C24: SUMIF Analysis | D24: Create conditional summaries | E24: 30 points
B25: Exercise 3 | C25: Dashboard | D25: Build a comprehensive financial dashboard | E25: 40 points
B28: Important Instructions
B30: 1. Use the Ohio_Master_Data.xlsx file as your data source
B31: 2. Build ALL formulas from scratch - do NOT copy values
B32: 3. Use absolute references ($A$1) where appropriate
B33: 4. Test your formulas to ensure they return correct values
B34: 5. Format numbers as currency where indicated
B35: 6. Save your work frequently
B38: Submission Requirements:
B40: • Submit your completed Ohio_Student_Project.xlsx file
B42: • Include your name and student ID in the file properties
B44: • Ensure all formulas are working correctly before submission

Sheet Exercise 1
A1: z
B2: EXERCISE 1: INDEX & MATCH FUNCTIONS
B4: INSTRUCTIONS: Use INDEX and MATCH functions to retrieve financial data from the Ohio_Master_Data.xlsx file. Your formula should look like: =INDEX(data_range, MATCH(store_id, store_range, 0), MATCH(category, category_range, 0)) Remember to use absolute references ($) for your lookup ranges!
B9: Task 1: Retrieve Single Values
B11: Store ID | C11: Category | D11: Your Formula | E11: Result
B12: 1237 | C12: Sales | D12: =INDEX('Financial data'!$C$5:$I$16, MATCH('Exercise 1'!C12,'Financial data'!$B$5:$B$16,0), MATCH('Exercise 1'!B12,'Financial data'!$C$4:$I$4,0)) -> 4602437 | E12: =D12 -> 4602437
B13: 0092 | C13: Net Income | D13: =INDEX('Financial data'!$C$5:$I$16, MATCH('Exercise 1'!C13,'Financial data'!$B$5:$B$16,0), MATCH('Exercise 1'!B13,'Financial data'!$C$4:$I$4,0)) -> -19450 | E13: =D13 -> -19450
B14: 9229 | C14: Inventory | D14: =INDEX('Financial data'!$C$5:$I$16, MATCH('Exercise 1'!C14,'Financial data'!$B$5:$B$16,0), MATCH('Exercise 1'!B14,'Financial data'!$C$4:$I$4,0)) -> 131996 | E14: =D14 -> 131996
B15: 8722 | C15: Gross Profit | D15: =INDEX('Financial data'!$C$5:$I$16, MATCH('Exercise 1'!C15,'Financial data'!$B$5:$B$16,0), MATCH('Exercise 1'!B15,'Financial data'!$C$4:$I$4,0)) -> 658493 | E15: =D15 -> 658493
B16: 08222 | C16: Cost of Goods Sold | D16: =INDEX('Financial data'!$C$5:$I$16, MATCH('Exercise 1'!C16,'Financial data'!$B$5:$B$16,0), MATCH('Exercise 1'!B16,'Financial data'!$C$4:$I$4,0)) -> 801102 | E16: =D16 -> 801102
B17: 7732 | C17: Sales | D17: =INDEX('Financial data'!$C$5:$I$16, MATCH('Exercise 1'!C17,'Financial data'!$B$5:$B$16,0), MATCH('Exercise 1'!B17,'Financial data'!$C$4:$I$4,0)) -> 2749689 | E17: =D17 -> 2749689
B18: 1141 | C18: Net Income | D18: =INDEX('Financial data'!$C$5:$I$16, MATCH('Exercise 1'!C18,'Financial data'!$B$5:$B$16,0), MATCH('Exercise 1'!B18,'Financial data'!$C$4:$I$4,0)) -> -93596 | E18: =D18 -> -93596
B21: Task 2: Complete the Financial Table
B23: Fill in the table below by creating INDEX/MATCH formulas for each cell. The rows represent different stores, and the columns represent different financial categories. Create ONE formula and copy it across all cells (use absolute references!)
B27: Category \ Store | C27: 1237 | D27: 0092 | E27: 9229 | F27: 8722
B28: Sales | C28: =INDEX('Financial data'!$C$5:$F$16,MATCH('Exercise 1'!B28,'Financial data'!$B$5:$B$16,0), MATCH('Exercise 1'!C27,'Financial data'!$C$4:$F$4,0)) -> 4602437 | D28: =INDEX('Financial data'!$C$5:$F$16,MATCH('Exercise 1'!B28,'Financial data'!$B$5:$B$16,0), MATCH('Exercise 1'!D27,'Financial data'!$C$4:$F$4,0)) -> 1044739 | E28: =INDEX('Financial data'!$C$5:$F$16,MATCH('Exercise 1'!B28,'Financial data'!$B$5:$B$16,0), MATCH('Exercise 1'!E27,'Financial data'!$C$4:$F$4,0)) -> 513628 | F28: =INDEX('Financial data'!$C$5:$F$16,MATCH('Exercise 1'!B28,'Financial data'!$B$5:$B$16,0), MATCH('Exercise 1'!F27,'Financial data'!$C$4:$F$4,0)) -> 1831990
B29: Cost of Goods Sold | C29: =INDEX('Financial data'!$C$5:$F$16,MATCH(B29,'Financial data'!$B$5:$B$16,0), MATCH('Exercise 1'!C27,'Financial data'!$C$4:$F$4,0)) -> 2608199 | D29: =INDEX('Financial data'!$C$5:$F$16,MATCH(B29,'Financial data'!$B$5:$B$16,0), MATCH('Exercise 1'!D27,'Financial data'!$C$4:$F$4,0)) -> 608869 | E29: =INDEX('Financial data'!$C$5:$F$16,MATCH(B29,'Financial data'!$B$5:$B$16,0), MATCH('Exercise 1'!E27,'Financial data'!$C$4:$F$4,0)) -> 340957 | F29: =INDEX('Financial data'!$C$5:$F$16,MATCH(B29,'Financial data'!$B$5:$B$16,0), MATCH('Exercise 1'!F27,'Financial data'!$C$4:$F$4,0)) -> 1173497
B30: Gross Profit | C30: =INDEX('Financial data'!$C$5:$F$16,MATCH(B30,'Financial data'!$B$5:$B$16,0), MATCH('Exercise 1'!C27,'Financial data'!$C$4:$F$4,0)) -> 1994238 | D30: =INDEX('Financial data'!$C$5:$F$16,MATCH(B30,'Financial data'!$B$5:$B$16,0), MATCH('Exercise 1'!D27,'Financial data'!$C$4:$F$4,0)) -> 435870 | E30: =INDEX('Financial data'!$C$5:$F$16,MATCH(B30,'Financial data'!$B$5:$B$16,0), MATCH('Exercise 1'!E27,'Financial data'!$C$4:$F$4,0)) -> 172671 | F30: =INDEX('Financial data'!$C$5:$F$16,MATCH(B30,'Financial data'!$B$5:$B$16,0), MATCH('Exercise 1'!F27,'Financial data'!$C$4:$F$4,0)) -> 658493
B31: Operating Expenses | C31: =INDEX('Financial data'!$C$5:$F$16,MATCH(B31,'Financial data'!$B$5:$B$16,0), MATCH('Exercise 1'!C27,'Financial data'!$C$4:$F$4,0)) -> 1031659 | D31: =INDEX('Financial data'!$C$5:$F$16,MATCH(B31,'Financial data'!$B$5:$B$16,0), MATCH('Exercise 1'!D27,'Financial data'!$C$4:$F$4,0)) -> 209507 | E31: =INDEX('Financial data'!$C$5:$F$16,MATCH(B31,'Financial data'!$B$5:$B$16,0), MATCH('Exercise 1'!E27,'Financial data'!$C$4:$F$4,0)) -> 85244 | F31: =INDEX('Financial data'!$C$5:$F$16,MATCH(B31,'Financial data'!$B$5:$B$16,0), MATCH('Exercise 1'!F27,'Financial data'!$C$4:$F$4,0)) -> 422663
B32: Net Income | C32: =INDEX('Financial data'!$C$5:$F$16,MATCH(B32,'Financial data'!$B$5:$B$16,0), MATCH('Exercise 1'!C27,'Financial data'!$C$4:$F$4,0)) -> -173519 | D32: =INDEX('Financial data'!$C$5:$F$16,MATCH(B32,'Financial data'!$B$5:$B$16,0), MATCH('Exercise 1'!D27,'Financial data'!$C$4:$F$4,0)) -> -19450 | E32: =INDEX('Financial data'!$C$5:$F$16,MATCH(B32,'Financial data'!$B$5:$B$16,0), MATCH('Exercise 1'!E27,'Financial data'!$C$4:$F$4,0)) -> -45347 | F32: =INDEX('Financial data'!$C$5:$F$16,MATCH(B32,'Financial data'!$B$5:$B$16,0), MATCH('Exercise 1'!F27,'Financial data'!$C$4:$F$4,0)) -> -318260
B34: © 2026 Mohim By Momina. All rights reserved

Sheet Exercise 2
B1: EXERCISE 2: SUMIF ANALYSIS
B3: INSTRUCTIONS: Use SUMIF functions to create conditional summaries of the Ohio Corporation financial data. SUMIF Syntax: =SUMIF(range, criteria, [sum_range]) Example: =SUMIF(Store_Range, "1237", Sales_Range) will sum all sales for store 1237
B8: Task 1: Total Sales by Store
B10: Use SUMIF to calculate the total Sales for each store listed below. Reference the Flattened_Data sheet in the master file.
B13: Store ID | C13: Store Name | D13: Your SUMIF Formula | E13: Total Sales
B14: 1237 | C14: Columbus Flagship | D14: =SUMIF('flattened data'!B5:$B$88,'Exercise 2'!B14,'flattened data'!D5:$D$88) -> 12772004 | E14: =D14 -> 12772004
B15: 0092 | C15: Cleveland Downtown | D15: =SUMIF('flattened data'!B6:$B$88,'Exercise 2'!B15,'flattened data'!D6:$D$88) -> 2963441 | E15: =D15 -> 2963441
B16: 9229 | C16: Cincinnati Mall | D16: =SUMIF('flattened data'!B7:$B$88,'Exercise 2'!B16,'flattened data'!D7:$D$88) -> 1376042 | E16: =D16 -> 1376042
B17: 8722 | C17: Dayton Plaza | D17: =SUMIF('flattened data'!B8:$B$88,'Exercise 2'!B17,'flattened data'!D8:$D$88) -> 5121701 | E17: =D17 -> 5121701
B18: 08222 | C18: Toledo Center | D18: =SUMIF('flattened data'!B9:$B$88,'Exercise 2'!B18,'flattened data'!D9:$D$88) -> 3342752 | E18: =D18 -> 3342752
B19: 7732 | C19: Akron Superstore | D19: =SUMIF('flattened data'!B10:$B$88,'Exercise 2'!B19,'flattened data'!D10:$D$88) -> 7488899 | E19: =D19 -> 7488899
B20: 1141 | C20: Youngstown Outlet | D20: =SUMIF('flattened data'!B11:$B$88,'Exercise 2'!B20,'flattened data'!D11:$D$88) -> 2852527 | E20: =D20 -> 2852527
B23: Task 2: Total Sales by Region
B25: Calculate total Sales for each region. You'll need to sum values from multiple stores in each region.
B28: Region | C28: Stores in Region | D28: Your Formula | E28: Total Sales
B29: Central | C29: 1237 | D29: =SUMIF('flattened data'!$B$5:$B$88,'Exercise 2'!C29,'flattened data'!$D$5:$D$88) -> 12772004 | E29: =D29 -> 12772004
B30: North | C30: 0092, 08222 | D30: =SUMIF('flattened data'!$B$5:$B$88, 92, 'flattened data'!D5:$D$88) + SUMIF('flattened data'!$B$5:$B$88, 8222, 'flattened data'!$D$5:$D$88) -> 6306193 | E30: =D30 -> 6306193
B31: South | C31: 9229 | D31: =SUMIF('flattened data'!$B$5:$B$88,'Exercise 2'!C31,'flattened data'!$D$5:$D$88) -> 1376042 | E31: =D31 -> 1376042
B32: East | C32: 7732, 1141 | D32: =SUMIF('flattened data'!$B$5:$B$88, 7732, 'flattened data'!D5:$D$88) + SUMIF('flattened data'!$B$5:$B$88, 1141, 'flattened data'!$D$5:$D$88) -> 10341426 | E32: =D32 -> 10341426
B33: West | C33: 8722 | D33: =SUMIF('flattened data'!$B$5:$B$88,'Exercise 2'!C33,'flattened data'!$D$5:$D$88) -> 5121701 | E33: =D33 -> 5121701
B36: Task 3: Total by Financial Category
B38: Calculate the total across ALL stores for each financial category. This will give you company-wide totals.
B41: Category | C41: Your Formula | D41: Total
B42: Sales | C42: =SUMIF('flattened data'!$C$5:$C$88,'Exercise 2'!B42,'flattened data'!$D$5:$D$88) -> 13014291 | D42: =C42 -> 13014291
B43: Cost of Goods Sold | C43: =SUMIF('flattened data'!$C$5:$C$88,'Exercise 2'!B43,'flattened data'!$D$5:$D$88) -> 7971195 | D43: =C43 -> 7971195
B44: Gross Profit | C44: =SUMIF('flattened data'!$C$5:$C$88,'Exercise 2'!B44,'flattened data'!$D$5:$D$88) -> 5043096 | D44: =C44 -> 5043096
B45: Operating Expenses | C45: =SUMIF('flattened data'!$C$5:$C$88,'Exercise 2'!B45,'flattened data'!$D$5:$D$88) -> 2674138 | D45: =C45 -> 2674138
B46: Net Income | C46: =SUMIF('flattened data'!$C$5:$C$88,'Exercise 2'!B46,'flattened data'!$D$5:$D$88) -> -1079290 | D46: =C46 -> -1079290
B47: Inventory | C47: =SUMIF('flattened data'!$C$5:$C$88,'Exercise 2'!B47,'flattened data'!$D$5:$D$88) -> 3758970 | D47: =C47 -> 3758970
B49: © 2026 Mohim By Momina. All rights reserved

Sheet Exercise 3 Dashboard
C1: EXERCISE 3: COMPREHENSIVE DASHBOARD
C3: INSTRUCTIONS: Create a professional financial dashboard that summarizes the Ohio Corporation's performance. Use all the skills you've learned: INDEX, MATCH, SUMIF, and formatting. Make it visually appealing and easy to understand.
C8: © 2026 Mohim By Momina. All rights reserved
C9: OHIO CORPORATION - SALE'S DASHBOARD
R18: TOTAL SALES
R19: =GETPIVOTDATA("Sales",'summary by store'!$B$17) -> 13014291
R22: TOTAL EXPENSES
R23: =GETPIVOTDATA("Total_Expenses",'summary by store'!$E$17) -> 6122386
R26: GROSS PROFIT
R27: ='summary by store'!E14 -> 5043096

Sheet Detail1
A1: Details for Sum of Profit_Margin
A3: Store_ID | B3: Store_Name | C3: Sales | D3: Gross_Profit | E3: Total_Expenses | F3: Net_Income | G3: Profit_Margin
A4: 7732 | B4: Akron Superstore | C4: 2749689 | D4: 893329 | E4: 1229277 | F4: -335948 | G4: -0.12217673
A5: 9229 | B5: Cincinnati Mall | C5: 513628 | D5: 172671 | E5: 218018 | F5: -45347 | G5: -0.088287632
A6: 0092 | B6: Cleveland Downtown | C6: 1044739 | D6: 435870 | E6: 455320 | F6: -19450 | G6: -0.01861709
A7: 1237 | B7: Columbus Flagship | C7: 4602437 | D7: 1994238 | E7: 2167757 | F7: -173519 | G7: -0.037701548
A8: 8722 | B8: Dayton Plaza | C8: 1831990 | D8: 658493 | E8: 976753 | F8: -318260 | G8: -0.17372366
A9: 08222 | B9: Toledo Center | C9: 1258403 | D9: 457301 | E9: 550471 | F9: -93170 | G9: -0.074038285
A10: 1141 | B10: Youngstown Outlet | C10: 1013405 | D10: 431194 | E10: 524790 | F10: -93596 | G10: -0.092357942

Sheet Financial data
B2: Financial Statements by Store
B4: Category | C4: 1237 | D4: 0092 | E4: 9229 | F4: 8722 | G4: 08222 | H4: 7732 | I4: 1141
B5: Sales | C5: 4602437 | D5: 1044739 | E5: 513628 | F5: 1831990 | G5: 1258403 | H5: 2749689 | I5: 1013405
B6: Cost of Goods Sold | C6: 2608199 | D6: 608869 | E6: 340957 | F6: 1173497 | G6: 801102 | H6: 1856360 | I6: 582211
B7: Gross Profit | C7: 1994238 | D7: 435870 | E7: 172671 | F7: 658493 | G7: 457301 | H7: 893329 | I7: 431194
B8: Operating Expenses | C8: 1031659 | D8: 209507 | E8: 85244 | F8: 422663 | G8: 277423 | H8: 457178 | I8: 190464
B9: Salaries Wages | C9: 619918 | D9: 127032 | E9: 74659 | F9: 300050 | G9: 154468 | H9: 388575 | I9: 181775
B10: Rent Lease | C10: 170183 | D10: 41728 | E10: 22544 | F10: 104077 | G10: 52091 | H10: 174629 | I10: 62831
B11: Utilities | C11: 55458 | D11: 24026 | E11: 7348 | F11: 53974 | G11: 19867 | H11: 66092 | I11: 21422
B12: Marketing Advertising | C12: 194315 | D12: 37974 | E12: 22037 | F12: 57443 | G12: 28180 | H12: 111380 | I12: 41081
B13: Depreciation | C13: 96224 | D13: 15053 | E13: 6186 | F13: 38546 | G13: 18442 | H13: 31423 | I13: 27217
B14: Inventory | C14: 1328143 | D14: 301292 | E14: 131996 | F14: 594317 | G14: 270745 | H14: 811836 | I14: 320641
B15: Accounts Receivable | C15: 244749 | D15: 136801 | E15: 44119 | F15: 204911 | G15: 97900 | H15: 284356 | I15: 73882
B16: Net Income | C16: -173519 | D16: -19450 | E16: -45347 | F16: -318260 | G16: -93170 | H16: -335948 | I16: -93596

Sheet summary by store
B3: Financial Summary by Store
B5: Store_ID | C5: Store_Name | D5: Sales | E5: Gross_Profit | F5: Total_Expenses | G5: Net_Income | H5: Profit_Margin
B6: 1237 | C6: Columbus Flagship | D6: 4602437 | E6: 1994238 | F6: 2167757 | G6: -173519 | H6: -0.037701548
B7: 0092 | C7: Cleveland Downtown | D7: 1044739 | E7: 435870 | F7: 455320 | G7: -19450 | H7: -0.01861709
B8: 9229 | C8: Cincinnati Mall | D8: 513628 | E8: 172671 | F8: 218018 | G8: -45347 | H8: -0.088287632
B9: 8722 | C9: Dayton Plaza | D9: 1831990 | E9: 658493 | F9: 976753 | G9: -318260 | H9: -0.17372366
B10: 08222 | C10: Toledo Center | D10: 1258403 | E10: 457301 | F10: 550471 | G10: -93170 | H10: -0.074038285
B11: 7732 | C11: Akron Superstore | D11: 2749689 | E11: 893329 | F11: 1229277 | G11: -335948 | H11: -0.12217673
B12: 1141 | C12: Youngstown Outlet | D12: 1013405 | E12: 431194 | F12: 524790 | G12: -93596 | H12: -0.092357942
E14: =SUM(E6:E12) -> 5043096 | G14: =SUM(G6:G12) -> -1079290
B17: Row Labels | C17: Sum of Sales | E17: Row Labels | F17: Sum of Total_Expenses | H17: Row Labels | I17: Sum of Gross_Profit
B18: Akron Superstore | C18: 2749689 | E18: Akron Superstore | F18: 1229277 | H18: Akron Superstore | I18: 0.177139
B19: Cincinnati Mall | C19: 513628 | E19: Cincinnati Mall | F19: 218018 | H19: Cincinnati Mall | I19: 0.034239086
B20: Cleveland Downtown | C20: 1044739 | E20: Cleveland Downtown | F20: 455320 | H20: Cleveland Downtown | I20: 0.086429051
B21: Columbus Flagship | C21: 4602437 | E21: Columbus Flagship | F21: 2167757 | H21: Columbus Flagship | I21: 0.39543923
B22: Dayton Plaza | C22: 1831990 | E22: Dayton Plaza | F22: 976753 | H22: Dayton Plaza | I22: 0.13057316
B23: Toledo Center | C23: 1258403 | E23: Toledo Center | F23: 550471 | H23: Toledo Center | I23: 0.090678623
B24: Youngstown Outlet | C24: 1013405 | E24: Youngstown Outlet | F24: 524790 | H24: Youngstown Outlet | I24: 0.085501843
B25: Grand Total | C25: 13014291 | E25: Grand Total | F25: 6122386 | H25: Grand Total | I25: 1

Sheet summary by category
B2: Financial Summary by Category
B4: Category | C4: Total | D4: Average | E4: Max | F4: Min
B5: Sales | C5: 13014291 | D5: 1859184.4 | E5: 4602437 | F5: 513628
B6: Cost of Goods Sold | C6: 7971195 | D6: 1138742.1 | E6: 2608199 | F6: 340957
B7: Gross Profit | C7: 5043096 | D7: 720442.29 | E7: 1994238 | F7: 172671
B8: Operating Expenses | C8: 2674138 | D8: 382019.71 | E8: 1031659 | F8: 85244
B9: Salaries Wages | C9: 1846477 | D9: 263782.43 | E9: 619918 | F9: 74659
B10: Rent Lease | C10: 628083 | D10: 89726.143 | E10: 174629 | F10: 22544
B11: Utilities | C11: 248187 | D11: 35455.286 | E11: 66092 | F11: 7348
B12: Marketing Advertising | C12: 492410 | D12: 70344.286 | E12: 194315 | F12: 22037
B13: Depreciation | C13: 233091 | D13: 33298.714 | E13: 96224 | F13: 6186
B14: Inventory | C14: 3758970 | D14: 536995.71 | E14: 1328143 | F14: 131996
B15: Accounts Receivable | C15: 1086718 | D15: 155245.43 | E15: 284356 | F15: 44119
B16: Net Income | C16: -1079290 | D16: -154184.29 | E16: -19450 | F16: -335948
B19: Row Labels | C19: Sum of Total
B20: Accounts Receivable | C20: 1086718
B21: Cost of Goods Sold | C21: 7971195
B22: Depreciation | C22: 233091
B23: Gross Profit | C23: 5043096
B24: Inventory | C24: 3758970
B25: Marketing Advertising | C25: 492410
B26: Net Income | C26: -1079290
B27: Operating Expenses | C27: 2674138
B28: Rent Lease | C28: 628083
B29: Salaries Wages | C29: 1846477
B30: Sales | C30: 13014291
B31: Utilities | C31: 248187
B32: Grand Total | C32: 35917366

Sheet flattened data
B2: Flattened Financial Data
B4: Store_ID | C4: Category | D4: Amount
B5: 1237 | C5: Sales | D5: 4602437
B6: 1237 | C6: Cost of Goods Sold | D6: 2608199
B7: 1237 | C7: Gross Profit | D7: 1994238
B8: 1237 | C8: Operating Expenses | D8: 1031659
B9: 1237 | C9: Salaries Wages | D9: 619918
B10: 1237 | C10: Rent Lease | D10: 170183
B11: 1237 | C11: Utilities | D11: 55458
B12: 1237 | C12: Marketing Advertising | D12: 194315
B13: 1237 | C13: Depreciation | D13: 96224
B14: 1237 | C14: Inventory | D14: 1328143
B15: 1237 | C15: Accounts Receivable | D15: 244749
B16: 1237 | C16: Net Income | D16: -173519
... B88: 1141 | C88: Net Income | D88: -93596

Sheet store info
B2: Store Information
B4: Store_ID | C4: Store_Name | D4: Location | E4: Store_Type | F4: Region
B5: 1237 | C5: Columbus Flagship | D5: Columbus, OH | E5: Flagship | F5: Central
B6: 0092 | C6: Cleveland Downtown | D6: Cleveland, OH | E6: Urban | F6: North
B7: 9229 | C7: Cincinnati Mall | D7: Cincinnati, OH | E7: Suburban | F7: South
B8: 8722 | C8: Dayton Plaza | D8: Dayton, OH | E8: Urban | F8: West
B9: 08222 | C9: Toledo Center | D9: Toledo, OH | E9: Suburban | F9: North
B10: 7732 | C10: Akron Superstore | D10: Akron, OH | E10: Urban | F10: East
B11: 1141 | C11: Youngstown Outlet | D11: Youngstown, OH | E11: Suburban | F11: East
